{"func_name": "Fread_c_len", "GNN_data": {"edges": [{"py/tuple": [4238141, 4238159]}, {"py/tuple": [4238159, 4238168]}, {"py/tuple": [4238159, 4238260]}, {"py/tuple": [4238168, 4238178]}, {"py/tuple": [4238178, 4238206]}, {"py/tuple": [4238206, 4238190]}, {"py/tuple": [4238190, 4238206]}, {"py/tuple": [4238190, "loopSeerDum"]}, {"py/tuple": [4238260, 4238529]}, {"py/tuple": [4238529, 4238541]}, {"py/tuple": [4238529, 4238272]}, {"py/tuple": [4238541, 4238561]}, {"py/tuple": [4238561, 4238543]}, {"py/tuple": [4238543, 4238561]}, {"py/tuple": [4238543, "loopSeerDum"]}, {"py/tuple": [4238272, 4238391]}, {"py/tuple": [4238391, 4238413]}, {"py/tuple": [4238413, 4238419]}, {"py/tuple": [4238419, 4238425]}, {"py/tuple": [4238425, 4238494]}, {"py/tuple": [4238494, 4238476]}, {"py/tuple": [4238494, 4238504]}, {"py/tuple": [4238476, 4238494]}, {"py/tuple": [4238504, 4238529]}, {"py/tuple": [4238504, "loopSeerDum"]}], "nodes": {"4238141": [], "4238159": [], "4238168": [{"py/tuple": ["Feq", {"py/tuple": ["RET_VAL", "fake_ret"]}, {"py/tuple": ["CONSTANT", "0x0"]}]}], "4238178": [], "4238206": [], "4238190": [], "loopSeerDum": [], "4238260": [{"py/tuple": ["Fne", {"py/tuple": ["RET_VAL", "fake_ret"]}, {"py/tuple": ["CONSTANT", "0x0"]}]}], "4238529": [], "4238541": [{"py/tuple": ["FSGE", {"py/tuple": ["CONSTANT", "0x2"]}, {"py/tuple": ["RET_VAL", "fake_ret"]}]}], "4238561": [], "4238543": [], "4238272": [{"py/tuple": ["FSLT", {"py/tuple": ["CONSTANT", "0x2"]}, {"py/tuple": ["RET_VAL", "fake_ret"]}]}], "4238391": [], "4238413": [], "4238419": [], "4238425": [], "4238494": [], "4238476": [], "4238504": []}}, "exe_name": "gzip", "package": "gzip"}