{"func_name": "Fsend_all_trees", "GNN_data": {"edges": [{"py/tuple": [4234160, 4234197]}, {"py/tuple": [4234197, 4234215]}, {"py/tuple": [4234215, 4234233]}, {"py/tuple": [4234233, 4234286]}, {"py/tuple": [4234286, 4234294]}, {"py/tuple": [4234286, 4234242]}, {"py/tuple": [4234294, 4234312]}, {"py/tuple": [4234312, 4234330]}, {"py/tuple": [4234330, "loopSeerDum"]}, {"py/tuple": [4234242, 4234282]}, {"py/tuple": [4234282, 4234286]}, {"py/tuple": [4234282, "loopSeerDum"]}], "nodes": {"4234160": [], "4234197": [], "4234215": [], "4234233": [], "4234286": [], "4234294": [{"py/tuple": ["FSGE", {"py/tuple": ["CONSTANT", "0x2"]}, {"py/tuple": ["REGISTER", "reg20"]}]}], "4234312": [], "4234330": [], "loopSeerDum": [], "4234242": [{"py/tuple": ["FSLT", {"py/tuple": ["CONSTANT", "0x1"]}, {"py/tuple": ["REGISTER", "reg20"]}]}], "4234282": []}}, "exe_name": "gzip", "package": "gzip"}